{
  "title": "Name this listing",
  "tagline": {
    "en": "Say something catchy",
    "zh": ""
  },
  "introduce": {
    "en": "Producer description",
    "zh": ""
  },
  "account_name": "Name of producer account",
  "public_key": "Public key for producer account",
  "org": {
    "name": "Organization name",
    "website": "",
    "email": "",
    "branding":{
      "logo": "logo-$account_name.png",
      "cover": "cover-$account_name.png"
    },
    "location": "City, Country",
    "social_network": {
      "steemit": "https://steemit.com/@your-awesome-project",
      "twitter": "https://twitter.com/your-awesome-project",
      "facebook": "https://www.facebook.com/your-awesome-project",
      "github": "https://github.com/your-awesome-project",
      "telegram": "https://t.me/your-awesome-project"
    }
  },
  "nodes": [
    {
      "location": {
        "id": "insert country code, refer to: https://countrycode.org/",
        "name": "Country"
      },
      "is_producer": false,
      "p2p_endpoint": "",
      "api_endpoint": "",
      "ssl_endpoint": ""
    }
  ]
}